[
    {
        "Title": "Make Booking with Coins",
        "SubTitle": " & Get Up to 35% Off",
        "Image": "https://oswalairtravels.com/images/oswal-flight.jpg"
    },
    {
        "Title": "Exciting Coin Offers on",
        "SubTitle": " All Summer Essentials",
        "Image": "https://img.freepik.com/free-vector/end-season-summer-sale_23-2148607742.jpg"
    },
    {
        "Title": "Shop, Play, Eat & More",
        "SubTitle": "Offers from 1 Coin",
        "Image": "https://www.thesun.co.uk/wp-content/uploads/2021/12/MT-SHOPPING-OFF-PLATT.jpg?strip=all&quality=100&w=1080&h=800&crop=1"
    },
    {
        "Title": "Get Up to 60% Off on",
        "SubTitle": "All Ramadan Feast Items",
        "Image": "https://img.freepik.com/premium-psd/ramadan-kareem-sale-banner-template-with-3d-online-shopping-mobile-applications_106244-1473.jpg"
    }
]